zk_watcher/__init__.py
zk_watcher/version.py
zk_watcher/zk_watcher.py
zk_watcher-0.4.0.dist-info/METADATA
zk_watcher-0.4.0.dist-info/WHEEL
zk_watcher-0.4.0.dist-info/entry_points.txt
zk_watcher-0.4.0.dist-info/top_level.txt
zk_watcher-0.4.0.dist-info/RECORD
