Metadata-Version: 2.1
Name: zk-watcher
Version: 0.4.0
Summary: Service Registration Daemon for Zookeeper
Home-page: https://github.com/Nextdoor/zkwatcher
Author: Nextdoor Engineering
Author-email: eng@nextdoor.com
License: Apache License, Version 2.0
Download-URL: http://pypi.python.org/pypi/zk_watcher#downloads
Keywords: apache
Platform: UNKNOWN
Classifier: Development Status :: 4 - Beta
Classifier: Topic :: Software Development
Classifier: License :: OSI Approved :: Apache Software License
Classifier: Intended Audience :: Developers
Classifier: Programming Language :: Python
Classifier: Operating System :: POSIX
Classifier: Natural Language :: English
Requires-Dist: nd-service-registry (>=1.0.0)
